{
  "app_name": "provisioning",
  "node_version": ">=16.0.0",
  "src_hash": "26eae85bbd3d1520af00bd095ab39f46a910f3db",
  "src_tag": "",
  "src_branch": "main",
  "patternfly_dependencies": ["UNMET DEPENDENCY @patternfly/react-core@4.276.11"],
  "rh_cloud_services_dependencies": ["UNMET DEPENDENCY @redhat-cloud-services/frontend-components-utilities@3.7.4","UNMET DEPENDENCY @redhat-cloud-services/frontend-components@3.11.2"],
  "travis": {
    "event_type": "",
    "build_number": "5940127611",
    "build_web_url": ""
  }
}
